journ/__init__.py
journ/main.py
journ_app-1.0.7.dist-info/METADATA
journ_app-1.0.7.dist-info/WHEEL
journ_app-1.0.7.dist-info/entry_points.txt
journ_app-1.0.7.dist-info/top_level.txt
journ_app-1.0.7.dist-info/RECORD
