Metadata-Version: 2.1
Name: journ-app
Version: 1.0.7
Summary: A CLI Journaling that honors your text editor of choice
Home-page: https://github.com/AlamarW/journ
Author: Austin Wiggins
Author-email: Austinlamarwiggins@gmail.com
License: UNKNOWN
Platform: UNKNOWN
Requires-Python: >=3.6
